{
    "elements": [
        {
            "element": {
                "element_type": "minecraft:single_pool_element",
                "location": "chronicle:wasteland/walker_bones/hand/metacarpal_left_1",
                "processors": [],
                "projection": "rigid"
            },
            "weight": 1
        },
        {
            "element": {
                "element_type": "minecraft:single_pool_element",
                "location": "chronicle:wasteland/walker_bones/hand/metacarpal_left_2",
                "processors": [],
                "projection": "rigid"
            },
            "weight": 1
        },
        {
            "element": {
                "element_type": "minecraft:single_pool_element",
                "location": "chronicle:wasteland/walker_bones/hand/metacarpal_right_1",
                "processors": [],
                "projection": "rigid"
            },
            "weight": 1
        },
        {
            "element": {
                "element_type": "minecraft:single_pool_element",
                "location": "chronicle:wasteland/walker_bones/hand/metacarpal_right_2",
                "processors": [],
                "projection": "rigid"
            },
            "weight": 1
        }
    ],
    "fallback": "minecraft:empty"
}